[
  {
    "heading": "Trending",
    "data": [
      {
        "id": "23456789",
        "authorName": "Rajat chauhan",
        "title": "We all hate you Mukesh | Sit down comedy by Rajat Chauhan",
        "videoCode": "KmKEh_m7XNg",
        "thumbnail_url": "https://i.ytimg.com/vi/KmKEh_m7XNg/hqdefault.jpg"
      },
      {
        "id": "23456789",
        "authorName": "Rajat chauhan",
        "title": "We all hate you Mukesh | Sit down comedy by Rajat Chauhan",
        "videoCode": "OLZoBJxlQBA",
        "thumbnail_url": "https://i.ytimg.com/vi/KmKEh_m7XNg/hqdefault.jpg"
      }
    ]
  },
  {
    "heading": "Trending",
    "data": [
      {
        "id": "23456789",
        "authorName": "Rajat chauhan",
        "title": "BEAUTY HACKS TO SPEED UP YOUR DAILY ROUTINE || Easy Girly Tips by 123 Go! Genius",
        "videoCode": "iKiTQ3ICqJg",
        "thumbnail_url": "https://i.ytimg.com/vi/KmKEh_m7XNg/hqdefault.jpg"
      },
      {
        "id": "23456789",
        "authorName": "Rajat chauhan",
        "title": "LOOKING GOOD! || Beauty Hacks To Look Like a Superstar In No Time",
        "videoCode": "UHUHmBk8DJ4",
        "thumbnail_url": "https://i.ytimg.com/vi/KmKEh_m7XNg/hqdefault.jpg"
      }
    ]
  }
]



